exchange_currency/__init__.py
exchange_currency/cli.py
exchange_currency/config.py
exchange_currency/rates.py
exchange_currency-0.2.0.dist-info/METADATA
exchange_currency-0.2.0.dist-info/WHEEL
exchange_currency-0.2.0.dist-info/entry_points.txt
exchange_currency-0.2.0.dist-info/RECORD
