Metadata-Version: 2.1
Name: exchange-currency
Version: 0.2.0
Summary: 
Author: mojoee
Author-email: 47809126+mojoee@users.noreply.github.com
Requires-Python: >=3.10,<4.0
Classifier: Programming Language :: Python :: 3
Classifier: Programming Language :: Python :: 3.10
Classifier: Programming Language :: Python :: 3.11
Requires-Dist: requests (>=2.31.0,<3.0.0)
